automotore/__init__.py
automotore/__main__.py
automotore/_version.py
automotore/_wh_main.py
automotore/wheelhouse.py
automotore-0.0.4.dist-info/LICENSE
automotore-0.0.4.dist-info/METADATA
automotore-0.0.4.dist-info/WHEEL
automotore-0.0.4.dist-info/entry_points.txt
automotore-0.0.4.dist-info/top_level.txt
automotore-0.0.4.dist-info/RECORD
