Metadata-Version: 2.1
Name: automotore
Version: 0.0.4
Summary: Self-contained Python wheelhouse generation for isolated environments
Home-page: https://github.com/jon-edward/automotore
Author: jon-edward
License: MIT
Keywords: python,wheelhouse,isolated,environment,pip
Classifier: Intended Audience :: Developers
Classifier: Topic :: Software Development :: Build Tools
Classifier: License :: OSI Approved :: MIT License
Classifier: Programming Language :: Python :: 3
Classifier: Programming Language :: Python :: 3.10
Classifier: Operating System :: OS Independent
License-File: LICENSE
